Persistence/_Persistence.c
Persistence/_Persistence.cpython-312-darwin.so
Persistence/__init__.py
Persistence/mapping.py
Persistence/tests/__init__.py
Persistence/tests/test_ec.py
Persistence/tests/test_mapping.py
Persistence/tests/test_persistent.py
persistence-5.4.dist-info/licenses/LICENSE.txt
persistence-5.4.dist-info/METADATA
persistence-5.4.dist-info/WHEEL
persistence-5.4.dist-info/top_level.txt
persistence-5.4.dist-info/RECORD
